{
  "src/slices": {
    "components": {
      "card": {
        "library": "src/slices",
        "id": "card",
        "name": "Card",
        "description": "Card",
        "model": {
          "id": "card",
          "type": "SharedSlice",
          "name": "Card",
          "description": "Card",
          "variations": [
            {
              "id": "default",
              "name": "Default",
              "docURL": "...",
              "version": "sktwi1xtmkfgx8626",
              "description": "Card",
              "primary": {
                "title": {
                  "type": "StructuredText",
                  "config": {
                    "single": "heading1",
                    "label": "Title",
                    "placeholder": "This is where it all begins..."
                  }
                },
                "description": {
                  "type": "StructuredText",
                  "config": {
                    "single": "paragraph",
                    "label": "Description",
                    "placeholder": "A nice description of your feature"
                  }
                }
              }
            }
          ]
        },
        "mocks": {
          "default": {
            "variation": "default",
            "name": "Default",
            "slice_type": "card",
            "items": [],
            "primary": {
              "title": [
                {
                  "type": "heading1",
                  "text": "Brand granular bandwidth",
                  "spans": []
                }
              ],
              "description": [
                {
                  "type": "paragraph",
                  "text": "Sint incididunt amet culpa ex proident. In consectetur Lorem id ex ullamco aute tempor exercitation ad esse anim sint consectetur tempor. Nostrud sit do anim nostrud labore.",
                  "spans": []
                }
              ]
            }
          }
        },
        "meta": {
          "fileName": "index",
          "isDirectory": true,
          "extension": "tsx"
        },
        "screenshotPaths": {}
      }
    }
  }
}